.gitignore
LICENSE
README.md
setup.py
pyalslib/ALSCatalog.py
pyalslib/ALSCatalogCache.py
pyalslib/ALSGraph.py
pyalslib/ALSRewriter.py
pyalslib/ALSSMT.py
pyalslib/Utility.py
pyalslib/YosysHelper.py
pyalslib/__init__.py
pyalslib.egg-info/PKG-INFO
pyalslib.egg-info/SOURCES.txt
pyalslib.egg-info/dependency_links.txt
pyalslib.egg-info/requires.txt
pyalslib.egg-info/top_level.txt
scripts/publish_package.sh