Metadata-Version: 2.2
Name: pyalslib
Version: 1.3.1
Summary: Python implementation of the Catalog-based Aig-rewriting Approximate Logic Synthesis approximation technique
Home-page: https://github.com/SalvatoreBarone/pyALSlib
Author: Salvatore Barone
Author-email: salvatore.barone@unina.it
Project-URL: Bug Reports, https://github.com/SalvatoreBarone/pyALSlib/issues
Project-URL: Source, https://github.com/SalvatoreBarone/pyALSlib
Keywords: Catalog-based Aig-rewriting Approximate Logic Synthesis approximation technique
Classifier: Intended Audience :: Information Technology
Classifier: Intended Audience :: Science/Research
Classifier: Topic :: Scientific/Engineering
Classifier: Topic :: Scientific/Engineering :: Electronic Design Automation (EDA)
Classifier: Topic :: Software Development :: Libraries
Classifier: Topic :: Software Development :: Embedded Systems
Classifier: Topic :: System :: Hardware
Classifier: License :: OSI Approved :: GNU General Public License v3 or later (GPLv3+)
Classifier: Programming Language :: Python :: 3.12
License-File: LICENSE
Requires-Dist: igraph
Requires-Dist: z3-solver
Requires-Dist: pyboolector
Requires-Dist: python-igraph
Requires-Dist: numpy
Requires-Dist: liberty-parser
Dynamic: author
Dynamic: author-email
Dynamic: classifier
Dynamic: description
Dynamic: home-page
Dynamic: keywords
Dynamic: project-url
Dynamic: requires-dist
Dynamic: summary
